aidrin/__init__.py
aidrin/_version.py
aidrin/logging.py
aidrin/main.py
aidrin/make_celery.py
aidrin/file_handling/file_parser.py
aidrin/file_handling/readers/base_reader.py
aidrin/file_handling/readers/csv_reader.py
aidrin/file_handling/readers/excel_reader.py
aidrin/file_handling/readers/hdf5_reader.py
aidrin/file_handling/readers/json_reader.py
aidrin/file_handling/readers/npz_reader.py
aidrin/structured_data_metrics/FAIRness_datacite.py
aidrin/structured_data_metrics/FAIRness_dcat.py
aidrin/structured_data_metrics/add_noise.py
aidrin/structured_data_metrics/class_imbalance.py
aidrin/structured_data_metrics/compare_representation_rate.py
aidrin/structured_data_metrics/completeness.py
aidrin/structured_data_metrics/conditional_demo_disp.py
aidrin/structured_data_metrics/correlation_score.py
aidrin/structured_data_metrics/duplicity.py
aidrin/structured_data_metrics/feature_relevance.py
aidrin/structured_data_metrics/outliers.py
aidrin/structured_data_metrics/privacy_measure.py
aidrin/structured_data_metrics/real_repreentation_rate.py
aidrin/structured_data_metrics/representation_rate.py
aidrin/structured_data_metrics/statistical_rate.py
aidrin/structured_data_metrics/summary_statistics.py
aidrin-2025.9.1.dist-info/licenses/AUTHORS.txt
aidrin-2025.9.1.dist-info/licenses/LICENSE.txt
aidrin-2025.9.1.dist-info/METADATA
aidrin-2025.9.1.dist-info/WHEEL
aidrin-2025.9.1.dist-info/top_level.txt
aidrin-2025.9.1.dist-info/RECORD
