Metadata-Version: 2.4
Name: aidrin
Version: 2025.9.1
Summary: A tool to evaluate the readiness of data for AI
Maintainer-email: Kaveen Hiniduma <hiniduma.1@osu.edu>, Suren Byna <byna.1@osu.edu>
License-File: LICENSE.txt
License-File: AUTHORS.txt
Requires-Dist: flask
Requires-Dist: matplotlib
Requires-Dist: dython
Requires-Dist: pandas
Requires-Dist: shap
Requires-Dist: h5py
Requires-Dist: celery
Requires-Dist: redis
Dynamic: license-file
